steno/__init__.py
steno/execute.py
steno/log.py
steno/main.py
steno/simplify.py
steno/token_metrics.py
steno/utils.py
steno_engine-0.1.2.dist-info/METADATA
steno_engine-0.1.2.dist-info/WHEEL
steno_engine-0.1.2.dist-info/entry_points.txt
steno_engine-0.1.2.dist-info/top_level.txt
steno_engine-0.1.2.dist-info/RECORD
