Metadata-Version: 2.4
Name: steno-engine
Version: 0.1.2
Summary: Prompt compression in Python
Author: Greg Lamp
Author-email: Greg Lamp <lamp.greg@gmail.com>
Requires-Python: >=3.8
Requires-Dist: spacy>=3.8.5
Requires-Dist: onnxruntime>=1.19.2
Requires-Dist: requests>=2.32.3
Requires-Dist: tiktoken>=0.9.0
Requires-Dist: transformers>=4.51.1
Requires-Dist: torch>=2.6.0
Requires-Dist: tqdm>=4.67.1
Requires-Dist: optimum>=1.24.0
Dynamic: author
Dynamic: requires-python
